boxobj_image/__init__.py
boxobj_image-0.1.0.dist-info/METADATA
boxobj_image-0.1.0.dist-info/WHEEL
boxobj_image-0.1.0.dist-info/RECORD
