Metadata-Version: 2.1
Name: boxobj-image
Version: 0.1.0
Summary: Utilities to support working with boxobj classes and Pillow images
Author: dschultz0
Author-email: dave@daveschultzconsulting.com
Requires-Python: >=3.8,<4.0
Classifier: Programming Language :: Python :: 3
Classifier: Programming Language :: Python :: 3.8
Classifier: Programming Language :: Python :: 3.9
Classifier: Programming Language :: Python :: 3.10
Classifier: Programming Language :: Python :: 3.11
Requires-Dist: Pillow (>=9.4.0,<10.0.0)
Requires-Dist: boxobj (>=0.1.0,<0.2.0)
